ordered_set-stubs/__init__.pyi
ordered_set_stubs-0.1.3.dist-info/LICENSE
ordered_set_stubs-0.1.3.dist-info/WHEEL
ordered_set_stubs-0.1.3.dist-info/METADATA
ordered_set_stubs-0.1.3.dist-info/RECORD
